{
  "words": [
    {
      "id": "2xDFf9QKB",
      "ru": "die Stelle, -n",
      "de": "место, должность",
      "statistics": {
        "success": 2,
        "fail": 0
      }
    },
    {
      "id": "Ih1rfaVmm",
      "ru": "arbeitlos",
      "de": "безработный",
      "statistics": {
        "success": 1,
        "fail": 1
      }
    },
    {
      "id": "liObbApVT",
      "ru": "der Friseur, -e",
      "de": "парикмахер",
      "statistics": {
        "success": 1,
        "fail": 0
      }
    },
    {
      "id": "9xadqix6x",
      "ru": "die Ausbildung, -en",
      "de": "обучение, образование",
      "statistics": {
        "success": 1,
        "fail": 0
      }
    },
    {
      "id": "A4coaIT2i",
      "ru": "der Beruf, -e",
      "de": "профессия",
      "statistics": {
        "success": 1,
        "fail": 0
      }
    },
    {
      "id": "Sh4rFJIOQ",
      "ru": "die Hochschule, -n",
      "de": "вуз",
      "statistics": {
        "success": 1,
        "fail": 0
      }
    },
    {
      "id": "kgYrCxGur",
      "ru": "die Schule, -n",
      "de": "школа",
      "statistics": {
        "success": 0,
        "fail": 1
      }
    },
    {
      "id": "x_rZm4u8-",
      "ru": "allein leben",
      "de": "жить одному",
      "statistics": {
        "success": 1,
        "fail": 0
      }
    }
  ],
  "collections": [
    {
      "id": "N09lKhbuG",
      "name": "Lektion 2. Lernwortschatz",
      "words": [
        "2xDFf9QKB",
        "Ih1rfaVmm",
        "liObbApVT",
        "9xadqix6x",
        "A4coaIT2i",
        "Sh4rFJIOQ",
        "kgYrCxGur",
        "x_rZm4u8-"
      ],
      "timestamp": 1545384206
    }
  ]
}